didery/__init__.py
didery/app.py
didery/cli.py
didery/didering.py
didery/routing.py
didery/controllers/__init__.py
didery/controllers/errors.py
didery/controllers/events.py
didery/controllers/history.py
didery/controllers/otp_blob.py
didery/controllers/relays.py
didery/controllers/static.py
didery/controllers/validation/__init__.py
didery/controllers/validation/factory.py
didery/controllers/validation/validating.py
didery/core/__init__.py
didery/core/resting.py
didery/crypto/__init__.py
didery/crypto/ecdsa.py
didery/crypto/eddsa.py
didery/crypto/factory.py
didery/db/__init__.py
didery/db/dbing.py
didery/did/__init__.py
didery/did/didering.py
didery/did/methods/__init__.py
didery/did/methods/dad.py
didery/flo/main.flo
didery/help/__init__.py
didery/help/helping.py
didery/models/__init__.py
didery/models/models.py
didery/static/__init__.py
didery/static/clean_tests.py
didery/static/favicon.ico
didery/static/main.html
didery/static/css/dashboard.css
didery/static/dist/main.js
didery/static/fonts/Raleway/Raleway-Black.ttf
didery/static/fonts/Raleway/Raleway-BlackItalic.ttf
didery/static/fonts/Raleway/Raleway-Bold.ttf
didery/static/fonts/Raleway/Raleway-BoldItalic.ttf
didery/static/fonts/Raleway/Raleway-ExtraBold.ttf
didery/static/fonts/Raleway/Raleway-ExtraBoldItalic.ttf
didery/static/fonts/Raleway/Raleway-ExtraLight.ttf
didery/static/fonts/Raleway/Raleway-ExtraLightItalic.ttf
didery/static/fonts/Raleway/Raleway-Italic.ttf
didery/static/fonts/Raleway/Raleway-Light.ttf
didery/static/fonts/Raleway/Raleway-LightItalic.ttf
didery/static/fonts/Raleway/Raleway-Medium.ttf
didery/static/fonts/Raleway/Raleway-MediumItalic.ttf
didery/static/fonts/Raleway/Raleway-Regular.ttf
didery/static/fonts/Raleway/Raleway-SemiBold.ttf
didery/static/fonts/Raleway/Raleway-SemiBoldItalic.ttf
didery/static/fonts/Raleway/Raleway-Thin.ttf
didery/static/fonts/Raleway/Raleway-ThinItalic.ttf
didery/static/images/logo-extended.png
didery/static/images/logo.png
didery-0.2.0.dist-info/LICENSE
didery-0.2.0.dist-info/METADATA
didery-0.2.0.dist-info/WHEEL
didery-0.2.0.dist-info/entry_points.txt
didery-0.2.0.dist-info/top_level.txt
didery-0.2.0.dist-info/RECORD
