Metadata-Version: 2.1
Name: didery
Version: 0.2.0
Summary: DIDery Key Management Server
Home-page: https://github.com/reputage/didery
Author: Nicholas Telfer, Brady Hammond, Michael Mendoza
Author-email: nick.telfer@consensys.net
License: Apache2
Platform: UNKNOWN
Classifier: Development Status :: 4 - Beta
Classifier: Intended Audience :: Developers
Classifier: License :: OSI Approved :: Apache Software License
Classifier: Operating System :: Unix
Classifier: Operating System :: POSIX
Classifier: Programming Language :: Python
Classifier: Programming Language :: Python :: 3.7
Classifier: Programming Language :: Python :: 3.6
Classifier: Programming Language :: Python :: 3.5
Classifier: Programming Language :: Python :: Implementation :: CPython
Classifier: Topic :: Utilities
Requires-Dist: arrow (>=0.10.0)
Requires-Dist: base58 (==1.0.2)
Requires-Dist: click
Requires-Dist: ecdsa (==0.13)
Requires-Dist: falcon (>=1.2)
Requires-Dist: fastecdsa (>=1.2.1)
Requires-Dist: ioflo (>=1.6.8)
Requires-Dist: libnacl (>=1.5.1)
Requires-Dist: lmdb
Requires-Dist: pytest-falcon (>=0.4.2)
Requires-Dist: simplejson (>=3.11.1)
